kubepath/__init__.py
kubepath/cli.py
kubepath/config.py
kubepath/console.py
kubepath/ai/__init__.py
kubepath/ai/gemini.py
kubepath/content/__init__.py
kubepath/content/loader.py
kubepath/content/renderer.py
kubepath/data/__init__.py
kubepath/data/modules.yaml
kubepath/data/schema.md
kubepath/data/chapters/01-kubernetes-basics.yaml
kubepath/data/chapters/02-cluster-architecture.yaml
kubepath/data/chapters/03-first-kubectl-commands.yaml
kubepath/data/chapters/04-understanding-pods.yaml
kubepath/data/chapters/05-building-container-images.yaml
kubepath/data/chapters/06-creating-pods.yaml
kubepath/data/chapters/07-pod-yaml-anatomy.yaml
kubepath/data/chapters/08-multi-container-pods.yaml
kubepath/data/chapters/09-debugging-pods.yaml
kubepath/data/chapters/10-labels-selectors-annotations.yaml
kubepath/data/chapters/11-namespaces.yaml
kubepath/data/chapters/12-intro-deployments.yaml
kubepath/data/chapters/13-scaling-rolling-updates.yaml
kubepath/data/chapters/14-rollbacks.yaml
kubepath/data/chapters/15-service-basics.yaml
kubepath/data/chapters/16-exposing-services.yaml
kubepath/data/chapters/17-service-discovery-dns.yaml
kubepath/data/chapters/18-intro-ingress.yaml
kubepath/data/chapters/19-configmaps-basics.yaml
kubepath/data/chapters/20-using-configmaps.yaml
kubepath/data/chapters/21-secrets.yaml
kubepath/data/chapters/22-resource-requests-limits.yaml
kubepath/data/chapters/23-serviceaccounts.yaml
kubepath/data/chapters/24-security-contexts.yaml
kubepath/data/chapters/25-rbac-basics.yaml
kubepath/data/chapters/26-admission-control.yaml
kubepath/data/chapters/27-volumes-basics.yaml
kubepath/data/chapters/28-persistent-volumes.yaml
kubepath/data/chapters/29-storage-classes.yaml
kubepath/data/chapters/30-jobs-cronjobs.yaml
kubepath/data/chapters/31-deployment-strategies.yaml
kubepath/data/chapters/32-helm-basics.yaml
kubepath/data/chapters/33-network-policies-basics.yaml
kubepath/data/chapters/34-network-policy-rules.yaml
kubepath/data/chapters/35-health-probes.yaml
kubepath-0.1.0.dist-info/METADATA
kubepath-0.1.0.dist-info/WHEEL
kubepath-0.1.0.dist-info/entry_points.txt
kubepath-0.1.0.dist-info/licenses/LICENSE
kubepath-0.1.0.dist-info/RECORD
