Metadata-Version: 2.4
Name: kubepath
Version: 0.1.0
Summary: Interactive CLI application for learning Kubernetes
Project-URL: Homepage, https://github.com/nithin-nk/kubepath
Project-URL: Documentation, https://github.com/nithin-nk/kubepath#readme
Project-URL: Repository, https://github.com/nithin-nk/kubepath.git
Project-URL: Issues, https://github.com/nithin-nk/kubepath/issues
Author-email: Nithin K Anil <nithin08anil@gmail.com>
License: Apache-2.0
License-File: LICENSE
Keywords: ckad,cli,devops,k8s,kubectl,kubernetes,learning
Classifier: Development Status :: 4 - Beta
Classifier: Environment :: Console
Classifier: Intended Audience :: Developers
Classifier: Intended Audience :: System Administrators
Classifier: License :: OSI Approved :: Apache Software License
Classifier: Operating System :: OS Independent
Classifier: Programming Language :: Python :: 3
Classifier: Programming Language :: Python :: 3.12
Classifier: Programming Language :: Python :: 3.13
Classifier: Topic :: Education
Classifier: Topic :: System :: Systems Administration
Requires-Python: >=3.12
Requires-Dist: google-genai>=1.0.0
Requires-Dist: kubernetes>=35.0.0
Requires-Dist: pyyaml>=6.0.3
Requires-Dist: rich>=14.3.1
Requires-Dist: typer>=0.21.1
